package com.appsee;

class rb
{
  public rb(v paramv, int paramInt)
  {
    this.k = new yb(this, paramv, paramInt);
  }
  
  /* Error */
  public void i()
  {
    // Byte code:
    //   0: aload_0
    //   1: monitorenter
    //   2: aload_0
    //   3: getfield 38	com/appsee/rb:i	Ljava/lang/Object;
    //   6: astore_1
    //   7: aload_1
    //   8: monitorenter
    //   9: aload_0
    //   10: getfield 36	com/appsee/rb:G	Z
    //   13: ifeq +19 -> 32
    //   16: aload_0
    //   17: iconst_0
    //   18: putfield 36	com/appsee/rb:G	Z
    //   21: aload_0
    //   22: getfield 32	com/appsee/rb:b	Landroid/os/Handler;
    //   25: aload_0
    //   26: getfield 34	com/appsee/rb:k	Ljava/lang/Runnable;
    //   29: invokevirtual 49	android/os/Handler:removeCallbacks	(Ljava/lang/Runnable;)V
    //   32: aload_1
    //   33: monitorexit
    //   34: aload_0
    //   35: monitorexit
    //   36: return
    //   37: astore_2
    //   38: aload_1
    //   39: monitorexit
    //   40: aload_2
    //   41: athrow
    //   42: astore_1
    //   43: aload_0
    //   44: monitorexit
    //   45: aload_1
    //   46: athrow
    // Local variable table:
    //   start	length	slot	name	signature
    //   0	47	0	this	rb
    //   42	4	1	localObject2	Object
    //   37	4	2	localObject3	Object
    // Exception table:
    //   from	to	target	type
    //   9	32	37	finally
    //   32	34	37	finally
    //   38	40	37	finally
    //   2	9	42	finally
    //   40	42	42	finally
  }
  
  /* Error */
  public void l()
  {
    // Byte code:
    //   0: aload_0
    //   1: monitorenter
    //   2: aload_0
    //   3: getfield 38	com/appsee/rb:i	Ljava/lang/Object;
    //   6: astore_1
    //   7: aload_1
    //   8: monitorenter
    //   9: aload_0
    //   10: getfield 36	com/appsee/rb:G	Z
    //   13: ifne +20 -> 33
    //   16: aload_0
    //   17: iconst_1
    //   18: putfield 36	com/appsee/rb:G	Z
    //   21: aload_0
    //   22: getfield 32	com/appsee/rb:b	Landroid/os/Handler;
    //   25: aload_0
    //   26: getfield 34	com/appsee/rb:k	Ljava/lang/Runnable;
    //   29: invokevirtual 54	android/os/Handler:post	(Ljava/lang/Runnable;)Z
    //   32: pop
    //   33: aload_1
    //   34: monitorexit
    //   35: aload_0
    //   36: monitorexit
    //   37: return
    //   38: astore_2
    //   39: aload_1
    //   40: monitorexit
    //   41: aload_2
    //   42: athrow
    //   43: astore_1
    //   44: aload_0
    //   45: monitorexit
    //   46: aload_1
    //   47: athrow
    // Local variable table:
    //   start	length	slot	name	signature
    //   0	48	0	this	rb
    //   43	4	1	localObject2	Object
    //   38	4	2	localObject3	Object
    // Exception table:
    //   from	to	target	type
    //   9	33	38	finally
    //   33	35	38	finally
    //   39	41	38	finally
    //   2	9	43	finally
    //   41	43	43	finally
  }
}


/* Location:              /Users/michael/Downloads/dex2jar-2.0/HappyFresh.jar!/com/appsee/rb.class
 * Java compiler version: 6 (50.0)
 * JD-Core Version:       0.7.1
 */