package com.appsee;

final class rg
  implements Runnable
{
  rg(v paramv, Object paramObject) {}
  
  /* Error */
  public void run()
  {
    // Byte code:
    //   0: aload_0
    //   1: getfield 19	com/appsee/rg:k	Lcom/appsee/v;
    //   4: invokeinterface 32 1 0
    //   9: aload_0
    //   10: getfield 21	com/appsee/rg:G	Ljava/lang/Object;
    //   13: astore_1
    //   14: aload_1
    //   15: monitorenter
    //   16: aload_0
    //   17: getfield 21	com/appsee/rg:G	Ljava/lang/Object;
    //   20: invokevirtual 35	java/lang/Object:notify	()V
    //   23: aload_1
    //   24: monitorexit
    //   25: return
    //   26: astore_2
    //   27: aload_1
    //   28: monitorexit
    //   29: aload_2
    //   30: athrow
    //   31: astore_1
    //   32: aload_1
    //   33: ldc 37
    //   35: invokestatic 42	com/appsee/AppseeBackgroundUploader:i	(Ljava/lang/String;)Ljava/lang/String;
    //   38: invokestatic 48	com/appsee/vd:l	(Ljava/lang/Throwable;Ljava/lang/String;)V
    //   41: aload_0
    //   42: getfield 21	com/appsee/rg:G	Ljava/lang/Object;
    //   45: astore_1
    //   46: aload_1
    //   47: monitorenter
    //   48: aload_0
    //   49: getfield 21	com/appsee/rg:G	Ljava/lang/Object;
    //   52: invokevirtual 35	java/lang/Object:notify	()V
    //   55: aload_1
    //   56: monitorexit
    //   57: return
    //   58: astore_2
    //   59: aload_1
    //   60: monitorexit
    //   61: aload_2
    //   62: athrow
    //   63: astore_2
    //   64: aload_0
    //   65: getfield 21	com/appsee/rg:G	Ljava/lang/Object;
    //   68: astore_1
    //   69: aload_1
    //   70: monitorenter
    //   71: aload_0
    //   72: getfield 21	com/appsee/rg:G	Ljava/lang/Object;
    //   75: invokevirtual 35	java/lang/Object:notify	()V
    //   78: aload_1
    //   79: monitorexit
    //   80: aload_2
    //   81: athrow
    //   82: astore_2
    //   83: aload_1
    //   84: monitorexit
    //   85: aload_2
    //   86: athrow
    // Local variable table:
    //   start	length	slot	name	signature
    //   0	87	0	this	rg
    //   31	2	1	localException	Exception
    //   26	4	2	localObject3	Object
    //   58	4	2	localObject4	Object
    //   63	18	2	localObject5	Object
    //   82	4	2	localObject6	Object
    // Exception table:
    //   from	to	target	type
    //   16	25	26	finally
    //   27	29	26	finally
    //   0	9	31	java/lang/Exception
    //   48	57	58	finally
    //   59	61	58	finally
    //   0	9	63	finally
    //   32	41	63	finally
    //   71	80	82	finally
    //   83	85	82	finally
  }
}


/* Location:              /Users/michael/Downloads/dex2jar-2.0/HappyFresh.jar!/com/appsee/rg.class
 * Java compiler version: 6 (50.0)
 * JD-Core Version:       0.7.1
 */