package com.appsee;

class yb
  implements Runnable
{
  yb(rb paramrb, v paramv, int paramInt) {}
  
  /* Error */
  public void run()
  {
    // Byte code:
    //   0: aload_0
    //   1: getfield 20	com/appsee/yb:G	Lcom/appsee/rb;
    //   4: invokestatic 34	com/appsee/rb:i	(Lcom/appsee/rb;)Ljava/lang/Object;
    //   7: astore_1
    //   8: aload_1
    //   9: monitorenter
    //   10: aload_0
    //   11: getfield 20	com/appsee/yb:G	Lcom/appsee/rb;
    //   14: invokestatic 37	com/appsee/rb:i	(Lcom/appsee/rb;)Z
    //   17: ifne +6 -> 23
    //   20: aload_1
    //   21: monitorexit
    //   22: return
    //   23: aload_1
    //   24: monitorexit
    //   25: aload_0
    //   26: getfield 22	com/appsee/yb:i	Lcom/appsee/v;
    //   29: invokeinterface 41 1 0
    //   34: aload_0
    //   35: getfield 20	com/appsee/yb:G	Lcom/appsee/rb;
    //   38: invokestatic 44	com/appsee/rb:i	(Lcom/appsee/rb;)Landroid/os/Handler;
    //   41: aload_0
    //   42: aload_0
    //   43: getfield 24	com/appsee/yb:k	I
    //   46: i2l
    //   47: invokevirtual 50	android/os/Handler:postDelayed	(Ljava/lang/Runnable;J)Z
    //   50: pop
    //   51: return
    //   52: astore_2
    //   53: aload_1
    //   54: monitorexit
    //   55: aload_2
    //   56: athrow
    //   57: astore_1
    //   58: aload_1
    //   59: ldc 52
    //   61: invokestatic 57	com/appsee/AppseeBackgroundUploader:i	(Ljava/lang/String;)Ljava/lang/String;
    //   64: invokestatic 63	com/appsee/vd:l	(Ljava/lang/Throwable;Ljava/lang/String;)V
    //   67: goto -33 -> 34
    // Local variable table:
    //   start	length	slot	name	signature
    //   0	70	0	this	yb
    //   57	2	1	localException	Exception
    //   52	4	2	localObject2	Object
    // Exception table:
    //   from	to	target	type
    //   10	22	52	finally
    //   23	25	52	finally
    //   53	55	52	finally
    //   0	10	57	java/lang/Exception
    //   25	34	57	java/lang/Exception
    //   55	57	57	java/lang/Exception
  }
}


/* Location:              /Users/michael/Downloads/dex2jar-2.0/HappyFresh.jar!/com/appsee/yb.class
 * Java compiler version: 6 (50.0)
 * JD-Core Version:       0.7.1
 */